cinpy/README.MD
cinpy/__init__.py
cinpy/requirements.txt
cinpy/thirdparty.json
cinpy-0.13.dist-info/LICENSE.rst
cinpy-0.13.dist-info/METADATA
cinpy-0.13.dist-info/WHEEL
cinpy-0.13.dist-info/top_level.txt
cinpy-0.13.dist-info/RECORD
